datafeeds/__init__.py
datafeeds/logger.py
datafeeds/client/__init__.py
datafeeds/client/fundfeeds.py
datafeeds/client/futurefeeds.py
datafeeds/client/indexfeeds.py
datafeeds/client/optionfeeds.py
datafeeds/client/stockfeeds.py
datafeeds/jqdatafeeds/__init__.py
datafeeds/jqdatafeeds/fundfeedsjqdata.py
datafeeds/jqdatafeeds/futurefeedsjqdata.py
datafeeds/jqdatafeeds/indexfeedsjqdata.py
datafeeds/jqdatafeeds/optionfeedsjqdata.py
datafeeds/jqdatafeeds/stockfeedsjqdata.py
datafeeds/tusharefeeds/__init__.py
datafeeds/tusharefeeds/futurefeedstushare.py
datafeeds/tusharefeeds/stockfeedstushare.py
datafeeds/utils/__init__.py
datafeeds/windclientfeeds/__init__.py
datafeeds/windclientfeeds/stockfeedswindclient.py
datafeeds/winddatabasefeeds/__init__.py
datafeeds/winddatabasefeeds/fundfeedswinddatabase.py
datafeeds/winddatabasefeeds/futurefeedswinddatabase.py
datafeeds/winddatabasefeeds/indexfeedswinddatabase.py
datafeeds/winddatabasefeeds/optionfeedswinddatabase.py
datafeeds/winddatabasefeeds/stockfeedswinddatabase.py
datafeeds-0.13.dist-info/LICENSE
datafeeds-0.13.dist-info/METADATA
datafeeds-0.13.dist-info/WHEEL
datafeeds-0.13.dist-info/top_level.txt
datafeeds-0.13.dist-info/RECORD
