Metadata-Version: 2.1
Name: datafeeds
Version: 0.13
Summary: Python Data Source
Home-page: UNKNOWN
Author: liuqiuxi
Author-email: liuqiuxi1990@gmail.com
License: UNKNOWN
Platform: UNKNOWN
Requires-Dist: pandas
